radops/__init__.py
radops/settings.py
radops/utils.py
radops/cli/__init__.py
radops/cli/common.py
radops/cli/config.py
radops/cli/data_lake.py
radops/cli/jobs.py
radops/data_lake/__init__.py
radops/data_lake/_file.py
radops/data_lake/_file_creator.py
radops/data_lake/cloud_ops.py
radops/jobs/__init__.py
radops/jobs/docker.py
radops/jobs/executor.py
radops/jobs/gcp.py
radops/serialization/__init__.py
radops/serialization/_deserialization.py
radops/serialization/_math.py
radops/serialization/_serialization.py
radops/tracking/__init__.py
radops/tracking/base.py
radops/tracking/mlflow.py
radops-0.12.0.dist-info/METADATA
radops-0.12.0.dist-info/WHEEL
radops-0.12.0.dist-info/entry_points.txt
radops-0.12.0.dist-info/top_level.txt
radops-0.12.0.dist-info/RECORD
