Metadata-Version: 2.1
Name: radops
Version: 0.12.0
Summary: ops tooling for Striveworks's R&D team
Project-URL: homepage, https://www.striveworks.com
Requires-Python: >=3.8
Requires-Dist: attrs
Requires-Dist: numpy
Requires-Dist: pydantic-settings
Requires-Dist: boto3
Requires-Dist: tqdm
Requires-Dist: rich
Requires-Dist: typer
Requires-Dist: requests
Requires-Dist: docker
Requires-Dist: fabric
Requires-Dist: google-cloud-compute
Requires-Dist: mlflow-skinny
Provides-Extra: dev
Requires-Dist: setuptools-scm ; extra == 'dev'
Requires-Dist: pre-commit ; extra == 'dev'
Provides-Extra: test
Requires-Dist: pytest ; extra == 'test'
Requires-Dist: coverage ; extra == 'test'
